DLMSFirmwareUpdater/config.toml
DLMSFirmwareUpdater/main.py
DLMS_Firmware_updater-0.4.10.dist-info/METADATA
DLMS_Firmware_updater-0.4.10.dist-info/WHEEL
DLMS_Firmware_updater-0.4.10.dist-info/entry_points.txt
DLMS_Firmware_updater-0.4.10.dist-info/top_level.txt
DLMS_Firmware_updater-0.4.10.dist-info/RECORD
