Metadata-Version: 2.2
Name: DLMS_Firmware_updater
Version: 0.4.10
Summary: dlms-spodes
Author-email: Serj Kotilevski <youserj@outlook.com>
Project-URL: Source, https://github.com/youserj/DLMSFirmwareUpdater_project
Keywords: dlms,spodes,client,firmware,update
Classifier: Programming Language :: Python :: 3
Classifier: License :: OSI Approved :: MIT License
Classifier: Operating System :: OS Independent
Requires-Python: >=3.12
Requires-Dist: DLMS-SPODES<0.82,>=0.81.9999
Requires-Dist: DLMS_SPODES_client<0.14,>=0.13.9999
Requires-Dist: DLMS-SPODES-communications<1.5,>=1.4.9
Requires-Dist: DLMSAdapter<0.6,>=0.5.9999
Requires-Dist: DLMSCommunicationProfile<0.1,>=0.0.3
Requires-Dist: pyinstaller>=6.2
Requires-Dist: build>=1.2.1
